LICENSE
README.md
requirements.txt
setup.cfg
setup.py
parallelio/__init__.py
parallelio/parallelio.py
parallelio.egg-info/PKG-INFO
parallelio.egg-info/SOURCES.txt
parallelio.egg-info/dependency_links.txt
parallelio.egg-info/top_level.txt