Metadata-Version: 1.1
Name: parallelio
Version: 0.9
Summary: Basic tools for working with natural language text data
Home-page: https://github.com/signaln/parallelio
Author: Signal N
Author-email: parallelio@signaln.com
License: MIT
Download-URL: https://github.com/signaln/parallelio/archive/0.9.tar.gz
Keywords: text,data,files,io,natural language processing
Platform: UNKNOWN
Classifier: Development Status :: 3 - Alpha
Classifier: Intended Audience :: Developers
Classifier: License :: OSI Approved :: MIT License
Classifier: Programming Language :: Python :: 3.3
Classifier: Programming Language :: Python :: 3.4
Classifier: Programming Language :: Python :: 3.5
